{
  "project_info": {
    "project_number": "266564919599",
    "project_id": "vrgamefirebase",
    "storage_bucket": "vrgamefirebase.firebasestorage.app"
  },
  "client": [
    {
      "client_info": {
        "mobilesdk_app_id": "1:266564919599:android:ebd50f1f68d3ac169fc1da",
        "android_client_info": {
          "package_name": "com.DefaultCompany.VRGolfMultiplayer"
        }
      },
      "oauth_client": [],
      "api_key": [
        {
          "current_key": "AIzaSyA4GIpi3ffaekXSQlEQtSGiVayuHjZ-e3E"
        }
      ],
      "services": {
        "appinvite_service": {
          "other_platform_oauth_client": []
        }
      }
    }
  ],
  "configuration_version": "1"
}